LICENSE.txt
MANIFEST.in
README.md
setup.cfg
setup.py
taffmat.py
taffmat.egg-info/PKG-INFO
taffmat.egg-info/SOURCES.txt
taffmat.egg-info/dependency_links.txt
taffmat.egg-info/top_level.txt