Metadata-Version: 1.1
Name: taffmat
Version: 0.4.0
Summary: Read and write Teac TAFFmat files.
Home-page: http://github.com/questrail/taffmat
Author: Matthew Rankin
Author-email: matthew@questrail.com
License: MIT
Platform: UNKNOWN
Classifier: Programming Language :: Python
Classifier: Programming Language :: Python :: 2
Classifier: Programming Language :: Python :: 2.7
Classifier: Programming Language :: Python :: 3
Classifier: Programming Language :: Python :: 3.3
Classifier: Programming Language :: Python :: 3.4
Classifier: License :: OSI Approved :: MIT License
Classifier: Development Status :: 3 - Alpha
Classifier: Operating System :: OS Independent
Classifier: Intended Audience :: Developers
Classifier: Topic :: Software Development :: Libraries :: Python Modules
Requires: numpy (>=1.6.0)
